<?xml version="1.0" encoding="UTF-8" standalone="no"?>
<?OntoDPSData docID="3370642" markupID="2092790" OntoTechnologyVersion="3.59.92.0"?>
<rdf:RDF xmlns:rdf="http://www.w3.org/1999/02/22-rdf-syntax-ns#" xmlns:BasicEntity="http://www.abbyy.com/ns/BasicEntity#" xmlns:rdfs="http://www.w3.org/2000/01/rdf-schema#" xmlns:Aux="http://www.abbyy.com/ns/Aux#">
	<BasicEntity:MoneySimplified rdf:nodeID="bnode39D675CC-A802-4381-BB19-A35640B6FA38">
		<BasicEntity:ms_major_currency xml:lang="en-US">Bulgarian levs</BasicEntity:ms_major_currency>
		<BasicEntity:ms_major_amount xml:lang="en-US">1.465</BasicEntity:ms_major_amount>
	</BasicEntity:MoneySimplified>
	<Aux:TextAnnotations rdf:nodeID="bnodeA9BB92CD-4489-4C14-B2AE-5103F19AB043">
		<Aux:document_text xml:lang="en-US">Police ordered a bus to park across one Sofia street to stop protesters reaching the president's office. A few stones were thrown in the direction of the building. In one of the biggest rallies, more than 10,000 people filled the city of Varna on the Danube River, where the national flag had been lowered at the municipality in support of the protests. ($1 = 1.4650 Bulgarian levs)</Aux:document_text>
		<Aux:annotation>
			<Aux:InstanceAnnotation rdf:nodeID="bnode890AF6C4-2626-484C-A7ED-7154FF19BD9F">
				<Aux:annotation_start rdf:datatype="http://www.w3.org/2001/XMLSchema#integer">360</Aux:annotation_start>
				<Aux:annotation_end rdf:datatype="http://www.w3.org/2001/XMLSchema#integer">381</Aux:annotation_end>
				<Aux:instance rdf:nodeID="bnode39D675CC-A802-4381-BB19-A35640B6FA38"/>
			</Aux:InstanceAnnotation>
		</Aux:annotation>
		<Aux:annotation>
			<Aux:PropertyAnnotation rdf:nodeID="bnode8AA0FC62-483E-4D48-BE52-29FDC578808D">
				<Aux:annotation_start rdf:datatype="http://www.w3.org/2001/XMLSchema#integer">360</Aux:annotation_start>
				<Aux:annotation_end rdf:datatype="http://www.w3.org/2001/XMLSchema#integer">366</Aux:annotation_end>
				<Aux:instance rdf:nodeID="bnode39D675CC-A802-4381-BB19-A35640B6FA38"/>
				<Aux:property_name xml:lang="en-US">http://www.abbyy.com/ns/BasicEntity#ms_major_amount</Aux:property_name>
				<Aux:property_value xml:lang="en-US">1.465</Aux:property_value>
			</Aux:PropertyAnnotation>
		</Aux:annotation>
		<Aux:annotation>
			<Aux:PropertyAnnotation rdf:nodeID="bnode589C1C3E-1BA2-4B45-A64E-CA1B6484A075">
				<Aux:annotation_start rdf:datatype="http://www.w3.org/2001/XMLSchema#integer">367</Aux:annotation_start>
				<Aux:annotation_end rdf:datatype="http://www.w3.org/2001/XMLSchema#integer">381</Aux:annotation_end>
				<Aux:instance rdf:nodeID="bnode39D675CC-A802-4381-BB19-A35640B6FA38"/>
				<Aux:property_name xml:lang="en-US">http://www.abbyy.com/ns/BasicEntity#ms_major_currency</Aux:property_name>
				<Aux:property_value xml:lang="en-US">Bulgarian levs</Aux:property_value>
			</Aux:PropertyAnnotation>
		</Aux:annotation>
	</Aux:TextAnnotations>
</rdf:RDF>