<?xml version="1.0" encoding="UTF-8" standalone="no"?>
<?OntoDPSData docID="3370708" markupID="2092790" OntoTechnologyVersion="3.59.92.0"?>
<rdf:RDF xmlns:rdf="http://www.w3.org/1999/02/22-rdf-syntax-ns#" xmlns:BasicEntity="http://www.abbyy.com/ns/BasicEntity#" xmlns:rdfs="http://www.w3.org/2000/01/rdf-schema#" xmlns:Aux="http://www.abbyy.com/ns/Aux#">
	<BasicEntity:MoneySimplified rdf:nodeID="bnodeE2A1419E-B7F4-4C8D-95ED-9A8A14265966">
		<BasicEntity:ms_major_currency xml:lang="en-US">ruble</BasicEntity:ms_major_currency>
		<BasicEntity:ms_major_amount xml:lang="en-US">1.1</BasicEntity:ms_major_amount>
	</BasicEntity:MoneySimplified>
	<BasicEntity:MoneySimplified rdf:nodeID="bnodeBBE6203B-277C-40F3-A0DD-62E8DE57C439">
		<BasicEntity:ms_major_currency xml:lang="en-US">kopecks</BasicEntity:ms_major_currency>
		<BasicEntity:ms_major_amount xml:lang="en-US">60</BasicEntity:ms_major_amount>
	</BasicEntity:MoneySimplified>
	<BasicEntity:MoneySimplified rdf:nodeID="bnodeBAC86344-1F9C-46C7-9A13-193B29C84211">
		<BasicEntity:ms_major_currency xml:lang="en-US">kopeck</BasicEntity:ms_major_currency>
		<BasicEntity:ms_major_amount xml:lang="en-US">1</BasicEntity:ms_major_amount>
	</BasicEntity:MoneySimplified>
	<Aux:TextAnnotations rdf:nodeID="bnode1B4E1FDC-BFB2-480E-86E3-93D4108C7209">
		<Aux:document_text xml:lang="en-US">The TELE2 network will be in operation in Kirov and key district centers of the Kirov region beginning from October 2009. These will include the cities of Kirovo-Chepetsk, Slobodskoy, Kotelnich, Orlov, Yurya, and other communities, which account for almost 60% of the total population in the region. The Company plans to further expand its coverage area in the near future. TELE2 offers the residents of the Kirov region just two tariff plans. The “Knockout” tariff has a very simple structure and will suit those who make calls to various phones in the Kirov region. One second of an outgoing call costs 1 kopeck with per-second billing from the second minute; the price for one outgoing SMS is 60 kopecks. The “Znai Nashikh” tariff will be more favorable for those who have already signed up their friends or family members  to TELE2 and who use this operator more often than others. In this case, outgoing calls and SMS to TELE2 phones in the Kirov region cost 10 kopecks per minute or one message. Outgoing calls and messages to phones administered by other cellular or landline operators in the region cost 1.1 ruble per minute or SMS. Calls are charged per minute. There is no subscription or connection fee in either tariff plan. Detailed information on tariff plan terms is available on the Company website and in information leaflets.</Aux:document_text>
		<Aux:annotation>
			<Aux:InstanceAnnotation rdf:nodeID="bnode4135483C-CCFA-44BE-AC9F-2EE315239C15">
				<Aux:annotation_start rdf:datatype="http://www.w3.org/2001/XMLSchema#integer">605</Aux:annotation_start>
				<Aux:annotation_end rdf:datatype="http://www.w3.org/2001/XMLSchema#integer">613</Aux:annotation_end>
				<Aux:instance rdf:nodeID="bnodeBAC86344-1F9C-46C7-9A13-193B29C84211"/>
			</Aux:InstanceAnnotation>
		</Aux:annotation>
		<Aux:annotation>
			<Aux:PropertyAnnotation rdf:nodeID="bnode7653C7B5-889D-4B31-B514-E95E739E4E1F">
				<Aux:annotation_start rdf:datatype="http://www.w3.org/2001/XMLSchema#integer">605</Aux:annotation_start>
				<Aux:annotation_end rdf:datatype="http://www.w3.org/2001/XMLSchema#integer">606</Aux:annotation_end>
				<Aux:instance rdf:nodeID="bnodeBAC86344-1F9C-46C7-9A13-193B29C84211"/>
				<Aux:property_name xml:lang="en-US">http://www.abbyy.com/ns/BasicEntity#ms_major_amount</Aux:property_name>
				<Aux:property_value xml:lang="en-US">1</Aux:property_value>
			</Aux:PropertyAnnotation>
		</Aux:annotation>
		<Aux:annotation>
			<Aux:PropertyAnnotation rdf:nodeID="bnode0E0BDDC2-29C0-42B8-B5CF-23FD3DF0AFF9">
				<Aux:annotation_start rdf:datatype="http://www.w3.org/2001/XMLSchema#integer">607</Aux:annotation_start>
				<Aux:annotation_end rdf:datatype="http://www.w3.org/2001/XMLSchema#integer">613</Aux:annotation_end>
				<Aux:instance rdf:nodeID="bnodeBAC86344-1F9C-46C7-9A13-193B29C84211"/>
				<Aux:property_name xml:lang="en-US">http://www.abbyy.com/ns/BasicEntity#ms_major_currency</Aux:property_name>
				<Aux:property_value xml:lang="en-US">kopeck</Aux:property_value>
			</Aux:PropertyAnnotation>
		</Aux:annotation>
		<Aux:annotation>
			<Aux:PropertyAnnotation rdf:nodeID="bnode1ADB3C62-3FC2-44B8-A52C-AB2E3E425829">
				<Aux:annotation_start rdf:datatype="http://www.w3.org/2001/XMLSchema#integer">696</Aux:annotation_start>
				<Aux:annotation_end rdf:datatype="http://www.w3.org/2001/XMLSchema#integer">698</Aux:annotation_end>
				<Aux:instance rdf:nodeID="bnodeBBE6203B-277C-40F3-A0DD-62E8DE57C439"/>
				<Aux:property_name xml:lang="en-US">http://www.abbyy.com/ns/BasicEntity#ms_major_amount</Aux:property_name>
				<Aux:property_value xml:lang="en-US">60</Aux:property_value>
			</Aux:PropertyAnnotation>
		</Aux:annotation>
		<Aux:annotation>
			<Aux:InstanceAnnotation rdf:nodeID="bnode4C1B3035-297B-4647-A319-380B4523F4B3">
				<Aux:annotation_start rdf:datatype="http://www.w3.org/2001/XMLSchema#integer">696</Aux:annotation_start>
				<Aux:annotation_end rdf:datatype="http://www.w3.org/2001/XMLSchema#integer">706</Aux:annotation_end>
				<Aux:instance rdf:nodeID="bnodeBBE6203B-277C-40F3-A0DD-62E8DE57C439"/>
			</Aux:InstanceAnnotation>
		</Aux:annotation>
		<Aux:annotation>
			<Aux:PropertyAnnotation rdf:nodeID="bnode16F9418F-9325-4B38-AC88-A498EE3EDEA0">
				<Aux:annotation_start rdf:datatype="http://www.w3.org/2001/XMLSchema#integer">699</Aux:annotation_start>
				<Aux:annotation_end rdf:datatype="http://www.w3.org/2001/XMLSchema#integer">706</Aux:annotation_end>
				<Aux:instance rdf:nodeID="bnodeBBE6203B-277C-40F3-A0DD-62E8DE57C439"/>
				<Aux:property_name xml:lang="en-US">http://www.abbyy.com/ns/BasicEntity#ms_major_currency</Aux:property_name>
				<Aux:property_value xml:lang="en-US">kopecks</Aux:property_value>
			</Aux:PropertyAnnotation>
		</Aux:annotation>
		<Aux:annotation>
			<Aux:InstanceAnnotation rdf:nodeID="bnode87559B9A-82BB-4720-A35B-1AC1CFC57C18">
				<Aux:annotation_start rdf:datatype="http://www.w3.org/2001/XMLSchema#integer">1112</Aux:annotation_start>
				<Aux:annotation_end rdf:datatype="http://www.w3.org/2001/XMLSchema#integer">1121</Aux:annotation_end>
				<Aux:instance rdf:nodeID="bnodeE2A1419E-B7F4-4C8D-95ED-9A8A14265966"/>
			</Aux:InstanceAnnotation>
		</Aux:annotation>
		<Aux:annotation>
			<Aux:PropertyAnnotation rdf:nodeID="bnode724B0F56-E2FE-4FCD-A805-6B708C4AD3BE">
				<Aux:annotation_start rdf:datatype="http://www.w3.org/2001/XMLSchema#integer">1112</Aux:annotation_start>
				<Aux:annotation_end rdf:datatype="http://www.w3.org/2001/XMLSchema#integer">1115</Aux:annotation_end>
				<Aux:instance rdf:nodeID="bnodeE2A1419E-B7F4-4C8D-95ED-9A8A14265966"/>
				<Aux:property_name xml:lang="en-US">http://www.abbyy.com/ns/BasicEntity#ms_major_amount</Aux:property_name>
				<Aux:property_value xml:lang="en-US">1.1</Aux:property_value>
			</Aux:PropertyAnnotation>
		</Aux:annotation>
		<Aux:annotation>
			<Aux:PropertyAnnotation rdf:nodeID="bnode3D266CA7-8409-4103-9017-44C080EE6ABC">
				<Aux:annotation_start rdf:datatype="http://www.w3.org/2001/XMLSchema#integer">1116</Aux:annotation_start>
				<Aux:annotation_end rdf:datatype="http://www.w3.org/2001/XMLSchema#integer">1121</Aux:annotation_end>
				<Aux:instance rdf:nodeID="bnodeE2A1419E-B7F4-4C8D-95ED-9A8A14265966"/>
				<Aux:property_name xml:lang="en-US">http://www.abbyy.com/ns/BasicEntity#ms_major_currency</Aux:property_name>
				<Aux:property_value xml:lang="en-US">ruble</Aux:property_value>
			</Aux:PropertyAnnotation>
		</Aux:annotation>
	</Aux:TextAnnotations>
</rdf:RDF>