<?xml version="1.0" encoding="UTF-8" standalone="no"?>
<?OntoDPSData docID="3372962" markupID="2092790" OntoTechnologyVersion="3.59.92.0"?>
<rdf:RDF xmlns:rdf="http://www.w3.org/1999/02/22-rdf-syntax-ns#" xmlns:BasicEntity="http://www.abbyy.com/ns/BasicEntity#" xmlns:rdfs="http://www.w3.org/2000/01/rdf-schema#" xmlns:Aux="http://www.abbyy.com/ns/Aux#">
	<BasicEntity:MoneySimplified rdf:nodeID="bnodeACFF1F23-151F-4514-92CD-C7484F8B327C">
		<BasicEntity:ms_major_currency xml:lang="en-US">ecus</BasicEntity:ms_major_currency>
		<BasicEntity:ms_major_amount xml:lang="en-US">15000</BasicEntity:ms_major_amount>
	</BasicEntity:MoneySimplified>
	<Aux:TextAnnotations rdf:nodeID="bnode2A212091-7258-4A8F-AAAD-3346F1D7DCC7">
		<Aux:document_text xml:lang="en-US">In 1418, the English laid siege to the town. The battle was fierce and the victors pitiless. The town was taken after 26 hours (15 according to English sources): 120 townspeople were killed at sword-point, while the others were spared only by paying a large ransom (15,000 ecus). The occupation that followed lasted 11 years. In December 1429, Étienne de Vignolles, also called La Hire, companion of Joan of Arc, retook the town. The English, not able to accept this fact, besieged the town in May 1431 with 12,000 men. The new siege lasted nearly six months. The town capitulated on 22 October after it had lost most of its defenders. The English promised honourable conditions to the survivors, but razed the town.</Aux:document_text>
		<Aux:annotation>
			<Aux:InstanceAnnotation rdf:nodeID="bnodeB6888C25-4507-4E96-81A3-592BE3F161C9">
				<Aux:annotation_start rdf:datatype="http://www.w3.org/2001/XMLSchema#integer">266</Aux:annotation_start>
				<Aux:annotation_end rdf:datatype="http://www.w3.org/2001/XMLSchema#integer">277</Aux:annotation_end>
				<Aux:instance rdf:nodeID="bnodeACFF1F23-151F-4514-92CD-C7484F8B327C"/>
			</Aux:InstanceAnnotation>
		</Aux:annotation>
		<Aux:annotation>
			<Aux:PropertyAnnotation rdf:nodeID="bnode67B30AE0-E566-4F2C-AAFF-BE38EA9157AE">
				<Aux:annotation_start rdf:datatype="http://www.w3.org/2001/XMLSchema#integer">266</Aux:annotation_start>
				<Aux:annotation_end rdf:datatype="http://www.w3.org/2001/XMLSchema#integer">272</Aux:annotation_end>
				<Aux:instance rdf:nodeID="bnodeACFF1F23-151F-4514-92CD-C7484F8B327C"/>
				<Aux:property_name xml:lang="en-US">http://www.abbyy.com/ns/BasicEntity#ms_major_amount</Aux:property_name>
				<Aux:property_value xml:lang="en-US">15000</Aux:property_value>
			</Aux:PropertyAnnotation>
		</Aux:annotation>
		<Aux:annotation>
			<Aux:PropertyAnnotation rdf:nodeID="bnodeE4AFB1B4-EC29-4B3B-AAEB-72B1D53C8C9C">
				<Aux:annotation_start rdf:datatype="http://www.w3.org/2001/XMLSchema#integer">273</Aux:annotation_start>
				<Aux:annotation_end rdf:datatype="http://www.w3.org/2001/XMLSchema#integer">277</Aux:annotation_end>
				<Aux:instance rdf:nodeID="bnodeACFF1F23-151F-4514-92CD-C7484F8B327C"/>
				<Aux:property_name xml:lang="en-US">http://www.abbyy.com/ns/BasicEntity#ms_major_currency</Aux:property_name>
				<Aux:property_value xml:lang="en-US">ecus</Aux:property_value>
			</Aux:PropertyAnnotation>
		</Aux:annotation>
	</Aux:TextAnnotations>
</rdf:RDF>