<?xml version="1.0" encoding="UTF-8" standalone="no"?>
<?OntoDPSData docID="3373812" markupID="2092790" OntoTechnologyVersion="3.59.92.0"?>
<rdf:RDF xmlns:rdf="http://www.w3.org/1999/02/22-rdf-syntax-ns#" xmlns:BasicEntity="http://www.abbyy.com/ns/BasicEntity#" xmlns:rdfs="http://www.w3.org/2000/01/rdf-schema#" xmlns:Aux="http://www.abbyy.com/ns/Aux#">
	<BasicEntity:MoneySimplified rdf:nodeID="bnode9DC7332B-A764-4332-85CD-BE992956108D">
		<BasicEntity:ms_major_currency xml:lang="en-US">US$</BasicEntity:ms_major_currency>
		<BasicEntity:ms_major_amount xml:lang="en-US">7509000000</BasicEntity:ms_major_amount>
	</BasicEntity:MoneySimplified>
	<BasicEntity:MoneySimplified rdf:nodeID="bnodeBC0FC0E7-C491-461E-9C93-F2698E46368D">
		<BasicEntity:ms_major_currency xml:lang="en-US">US$</BasicEntity:ms_major_currency>
		<BasicEntity:ms_major_amount xml:lang="en-US">718000000</BasicEntity:ms_major_amount>
	</BasicEntity:MoneySimplified>
	<BasicEntity:MoneySimplified rdf:nodeID="bnodeCBB607CB-548A-4689-85CB-01E2F09ABEA6">
		<BasicEntity:ms_major_currency xml:lang="en-US">US$</BasicEntity:ms_major_currency>
		<BasicEntity:ms_major_amount xml:lang="en-US">9725000000</BasicEntity:ms_major_amount>
	</BasicEntity:MoneySimplified>
	<BasicEntity:MoneySimplified rdf:nodeID="bnodeC111942D-CA6D-49DF-99F1-0FB9717BC41D">
		<BasicEntity:ms_major_currency xml:lang="en-US">U.S. dollars</BasicEntity:ms_major_currency>
		<BasicEntity:ms_major_amount xml:lang="en-US">718000000</BasicEntity:ms_major_amount>
	</BasicEntity:MoneySimplified>
	<BasicEntity:MoneySimplified rdf:nodeID="bnodeC28C7172-4AE5-460C-A654-0E7902C23290">
		<BasicEntity:ms_major_currency xml:lang="en-US">pesetas</BasicEntity:ms_major_currency>
		<BasicEntity:ms_major_amount xml:lang="en-US">500</BasicEntity:ms_major_amount>
	</BasicEntity:MoneySimplified>
	<BasicEntity:MoneySimplified rdf:nodeID="bnode38278070-3826-47B4-AB1A-23B6F4BD0FF1">
		<BasicEntity:ms_major_currency xml:lang="en-US">Spanish pesetas</BasicEntity:ms_major_currency>
		<BasicEntity:ms_major_amount xml:lang="en-US">177000000</BasicEntity:ms_major_amount>
	</BasicEntity:MoneySimplified>
	<BasicEntity:MoneySimplified rdf:nodeID="bnode058CF39B-FEC3-4D6A-A686-2E45EAE2E357">
		<BasicEntity:ms_major_currency xml:lang="en-US">Spanish pesetas</BasicEntity:ms_major_currency>
		<BasicEntity:ms_major_amount xml:lang="en-US">5240000000</BasicEntity:ms_major_amount>
	</BasicEntity:MoneySimplified>
	<Aux:TextAnnotations rdf:nodeID="bnode4BEC179F-4DB6-4110-A388-8BCE6433FD0D">
		<Aux:document_text xml:lang="en-US">The value of the reserves was known at the time by various official publications. The New York Times reported on August 7, 1936, that the Spanish gold reserves in Madrid were worth 718 million U.S. dollars at the time. Such figures corresponded to 635 tonnes of fine gold, or 20.42 million troy ounces. According to the statistics of the Bank of Spain as published in the official Spanish government newspaper on July 1, the existent gold reserves on June 30, 1936, three weeks before the start of the conflict, reached a value of 5,240 million Spanish pesetas. Viñas calculated that the US$718 million of 1936 were equivalent, adjusted for inflation indexes, to US$9,725 million in 2005. In comparison, the Spanish gold reserves available in September of the same year were worth US$7,509 million. In 1782, the Bank of Spain was established as a joint stock company (as its French and English counterparts) with a capital of 177 million Spanish pesetas, which was distributed among 354,000 nominative shares of 500 pesetas each. Despite not being a state-owned bank, the institution was subject to the control of both the government, which had the power to appoint the Bank's governor, and the Ministry of Finance, which appointed various members of the Bank's General Council.</Aux:document_text>
		<Aux:annotation>
			<Aux:InstanceAnnotation rdf:nodeID="bnode794F1241-29E6-4C78-8F0A-9196818CBC17">
				<Aux:annotation_start rdf:datatype="http://www.w3.org/2001/XMLSchema#integer">181</Aux:annotation_start>
				<Aux:annotation_end rdf:datatype="http://www.w3.org/2001/XMLSchema#integer">205</Aux:annotation_end>
				<Aux:instance rdf:nodeID="bnodeC111942D-CA6D-49DF-99F1-0FB9717BC41D"/>
			</Aux:InstanceAnnotation>
		</Aux:annotation>
		<Aux:annotation>
			<Aux:PropertyAnnotation rdf:nodeID="bnode9C8445C1-AFA5-42DB-9711-D941CADB3267">
				<Aux:annotation_start rdf:datatype="http://www.w3.org/2001/XMLSchema#integer">181</Aux:annotation_start>
				<Aux:annotation_end rdf:datatype="http://www.w3.org/2001/XMLSchema#integer">192</Aux:annotation_end>
				<Aux:instance rdf:nodeID="bnodeC111942D-CA6D-49DF-99F1-0FB9717BC41D"/>
				<Aux:property_name xml:lang="en-US">http://www.abbyy.com/ns/BasicEntity#ms_major_amount</Aux:property_name>
				<Aux:property_value xml:lang="en-US">718000000</Aux:property_value>
			</Aux:PropertyAnnotation>
		</Aux:annotation>
		<Aux:annotation>
			<Aux:PropertyAnnotation rdf:nodeID="bnode619425F3-EA83-4428-BE15-D8B1EB00DAC0">
				<Aux:annotation_start rdf:datatype="http://www.w3.org/2001/XMLSchema#integer">193</Aux:annotation_start>
				<Aux:annotation_end rdf:datatype="http://www.w3.org/2001/XMLSchema#integer">205</Aux:annotation_end>
				<Aux:instance rdf:nodeID="bnodeC111942D-CA6D-49DF-99F1-0FB9717BC41D"/>
				<Aux:property_name xml:lang="en-US">http://www.abbyy.com/ns/BasicEntity#ms_major_currency</Aux:property_name>
				<Aux:property_value xml:lang="en-US">U.S. dollars</Aux:property_value>
			</Aux:PropertyAnnotation>
		</Aux:annotation>
		<Aux:annotation>
			<Aux:PropertyAnnotation rdf:nodeID="bnode2D64FCA3-F547-4261-976A-EF4DFBF18AF3">
				<Aux:annotation_start rdf:datatype="http://www.w3.org/2001/XMLSchema#integer">531</Aux:annotation_start>
				<Aux:annotation_end rdf:datatype="http://www.w3.org/2001/XMLSchema#integer">544</Aux:annotation_end>
				<Aux:instance rdf:nodeID="bnode058CF39B-FEC3-4D6A-A686-2E45EAE2E357"/>
				<Aux:property_name xml:lang="en-US">http://www.abbyy.com/ns/BasicEntity#ms_major_amount</Aux:property_name>
				<Aux:property_value xml:lang="en-US">5240000000</Aux:property_value>
			</Aux:PropertyAnnotation>
		</Aux:annotation>
		<Aux:annotation>
			<Aux:InstanceAnnotation rdf:nodeID="bnode653663A0-2D30-415F-8464-08F434B19817">
				<Aux:annotation_start rdf:datatype="http://www.w3.org/2001/XMLSchema#integer">531</Aux:annotation_start>
				<Aux:annotation_end rdf:datatype="http://www.w3.org/2001/XMLSchema#integer">560</Aux:annotation_end>
				<Aux:instance rdf:nodeID="bnode058CF39B-FEC3-4D6A-A686-2E45EAE2E357"/>
			</Aux:InstanceAnnotation>
		</Aux:annotation>
		<Aux:annotation>
			<Aux:PropertyAnnotation rdf:nodeID="bnodeF4FE50A8-38FD-4120-B9DC-9B03928832F7">
				<Aux:annotation_start rdf:datatype="http://www.w3.org/2001/XMLSchema#integer">545</Aux:annotation_start>
				<Aux:annotation_end rdf:datatype="http://www.w3.org/2001/XMLSchema#integer">560</Aux:annotation_end>
				<Aux:instance rdf:nodeID="bnode058CF39B-FEC3-4D6A-A686-2E45EAE2E357"/>
				<Aux:property_name xml:lang="en-US">http://www.abbyy.com/ns/BasicEntity#ms_major_currency</Aux:property_name>
				<Aux:property_value xml:lang="en-US">Spanish pesetas</Aux:property_value>
			</Aux:PropertyAnnotation>
		</Aux:annotation>
		<Aux:annotation>
			<Aux:InstanceAnnotation rdf:nodeID="bnode954B99E9-AEB2-4DA9-B10F-BC65A373976B">
				<Aux:annotation_start rdf:datatype="http://www.w3.org/2001/XMLSchema#integer">588</Aux:annotation_start>
				<Aux:annotation_end rdf:datatype="http://www.w3.org/2001/XMLSchema#integer">602</Aux:annotation_end>
				<Aux:instance rdf:nodeID="bnodeBC0FC0E7-C491-461E-9C93-F2698E46368D"/>
			</Aux:InstanceAnnotation>
		</Aux:annotation>
		<Aux:annotation>
			<Aux:PropertyAnnotation rdf:nodeID="bnodeC914CE51-076F-4D10-A0AC-E5D7A1A0141A">
				<Aux:annotation_start rdf:datatype="http://www.w3.org/2001/XMLSchema#integer">588</Aux:annotation_start>
				<Aux:annotation_end rdf:datatype="http://www.w3.org/2001/XMLSchema#integer">591</Aux:annotation_end>
				<Aux:instance rdf:nodeID="bnodeBC0FC0E7-C491-461E-9C93-F2698E46368D"/>
				<Aux:property_name xml:lang="en-US">http://www.abbyy.com/ns/BasicEntity#ms_major_currency</Aux:property_name>
				<Aux:property_value xml:lang="en-US">US$</Aux:property_value>
			</Aux:PropertyAnnotation>
		</Aux:annotation>
		<Aux:annotation>
			<Aux:PropertyAnnotation rdf:nodeID="bnodeB7CD567E-42D1-4E20-811E-C69C33794D9D">
				<Aux:annotation_start rdf:datatype="http://www.w3.org/2001/XMLSchema#integer">591</Aux:annotation_start>
				<Aux:annotation_end rdf:datatype="http://www.w3.org/2001/XMLSchema#integer">602</Aux:annotation_end>
				<Aux:instance rdf:nodeID="bnodeBC0FC0E7-C491-461E-9C93-F2698E46368D"/>
				<Aux:property_name xml:lang="en-US">http://www.abbyy.com/ns/BasicEntity#ms_major_amount</Aux:property_name>
				<Aux:property_value xml:lang="en-US">718000000</Aux:property_value>
			</Aux:PropertyAnnotation>
		</Aux:annotation>
		<Aux:annotation>
			<Aux:PropertyAnnotation rdf:nodeID="bnode6310813C-BAA0-41A1-85FE-B750FB214182">
				<Aux:annotation_start rdf:datatype="http://www.w3.org/2001/XMLSchema#integer">663</Aux:annotation_start>
				<Aux:annotation_end rdf:datatype="http://www.w3.org/2001/XMLSchema#integer">666</Aux:annotation_end>
				<Aux:instance rdf:nodeID="bnodeCBB607CB-548A-4689-85CB-01E2F09ABEA6"/>
				<Aux:property_name xml:lang="en-US">http://www.abbyy.com/ns/BasicEntity#ms_major_currency</Aux:property_name>
				<Aux:property_value xml:lang="en-US">US$</Aux:property_value>
			</Aux:PropertyAnnotation>
		</Aux:annotation>
		<Aux:annotation>
			<Aux:InstanceAnnotation rdf:nodeID="bnodeF617E1E7-DA4C-45CB-9154-2333116E7DA1">
				<Aux:annotation_start rdf:datatype="http://www.w3.org/2001/XMLSchema#integer">663</Aux:annotation_start>
				<Aux:annotation_end rdf:datatype="http://www.w3.org/2001/XMLSchema#integer">679</Aux:annotation_end>
				<Aux:instance rdf:nodeID="bnodeCBB607CB-548A-4689-85CB-01E2F09ABEA6"/>
			</Aux:InstanceAnnotation>
		</Aux:annotation>
		<Aux:annotation>
			<Aux:PropertyAnnotation rdf:nodeID="bnode724B6C2C-B325-4960-AFAB-E0AE9F8CF964">
				<Aux:annotation_start rdf:datatype="http://www.w3.org/2001/XMLSchema#integer">666</Aux:annotation_start>
				<Aux:annotation_end rdf:datatype="http://www.w3.org/2001/XMLSchema#integer">679</Aux:annotation_end>
				<Aux:instance rdf:nodeID="bnodeCBB607CB-548A-4689-85CB-01E2F09ABEA6"/>
				<Aux:property_name xml:lang="en-US">http://www.abbyy.com/ns/BasicEntity#ms_major_amount</Aux:property_name>
				<Aux:property_value xml:lang="en-US">9725000000</Aux:property_value>
			</Aux:PropertyAnnotation>
		</Aux:annotation>
		<Aux:annotation>
			<Aux:InstanceAnnotation rdf:nodeID="bnodeBCAF211A-5CAA-4366-9614-7579C52A13A3">
				<Aux:annotation_start rdf:datatype="http://www.w3.org/2001/XMLSchema#integer">781</Aux:annotation_start>
				<Aux:annotation_end rdf:datatype="http://www.w3.org/2001/XMLSchema#integer">797</Aux:annotation_end>
				<Aux:instance rdf:nodeID="bnode9DC7332B-A764-4332-85CD-BE992956108D"/>
			</Aux:InstanceAnnotation>
		</Aux:annotation>
		<Aux:annotation>
			<Aux:PropertyAnnotation rdf:nodeID="bnodeAF286FE0-8FE1-457D-8455-FEEC86A518E1">
				<Aux:annotation_start rdf:datatype="http://www.w3.org/2001/XMLSchema#integer">781</Aux:annotation_start>
				<Aux:annotation_end rdf:datatype="http://www.w3.org/2001/XMLSchema#integer">784</Aux:annotation_end>
				<Aux:instance rdf:nodeID="bnode9DC7332B-A764-4332-85CD-BE992956108D"/>
				<Aux:property_name xml:lang="en-US">http://www.abbyy.com/ns/BasicEntity#ms_major_currency</Aux:property_name>
				<Aux:property_value xml:lang="en-US">US$</Aux:property_value>
			</Aux:PropertyAnnotation>
		</Aux:annotation>
		<Aux:annotation>
			<Aux:PropertyAnnotation rdf:nodeID="bnode7719109C-7ADD-41BA-8FB0-3D86D495D590">
				<Aux:annotation_start rdf:datatype="http://www.w3.org/2001/XMLSchema#integer">784</Aux:annotation_start>
				<Aux:annotation_end rdf:datatype="http://www.w3.org/2001/XMLSchema#integer">797</Aux:annotation_end>
				<Aux:instance rdf:nodeID="bnode9DC7332B-A764-4332-85CD-BE992956108D"/>
				<Aux:property_name xml:lang="en-US">http://www.abbyy.com/ns/BasicEntity#ms_major_amount</Aux:property_name>
				<Aux:property_value xml:lang="en-US">7509000000</Aux:property_value>
			</Aux:PropertyAnnotation>
		</Aux:annotation>
		<Aux:annotation>
			<Aux:PropertyAnnotation rdf:nodeID="bnode56F8A04B-D3F7-4951-A9E1-CFB0021F8683">
				<Aux:annotation_start rdf:datatype="http://www.w3.org/2001/XMLSchema#integer">926</Aux:annotation_start>
				<Aux:annotation_end rdf:datatype="http://www.w3.org/2001/XMLSchema#integer">937</Aux:annotation_end>
				<Aux:instance rdf:nodeID="bnode38278070-3826-47B4-AB1A-23B6F4BD0FF1"/>
				<Aux:property_name xml:lang="en-US">http://www.abbyy.com/ns/BasicEntity#ms_major_amount</Aux:property_name>
				<Aux:property_value xml:lang="en-US">177000000</Aux:property_value>
			</Aux:PropertyAnnotation>
		</Aux:annotation>
		<Aux:annotation>
			<Aux:InstanceAnnotation rdf:nodeID="bnodeE33753C7-4975-4A7D-B621-E81D7DEF0930">
				<Aux:annotation_start rdf:datatype="http://www.w3.org/2001/XMLSchema#integer">926</Aux:annotation_start>
				<Aux:annotation_end rdf:datatype="http://www.w3.org/2001/XMLSchema#integer">953</Aux:annotation_end>
				<Aux:instance rdf:nodeID="bnode38278070-3826-47B4-AB1A-23B6F4BD0FF1"/>
			</Aux:InstanceAnnotation>
		</Aux:annotation>
		<Aux:annotation>
			<Aux:PropertyAnnotation rdf:nodeID="bnode0EFB984A-005E-4E89-8157-6A224E536AC9">
				<Aux:annotation_start rdf:datatype="http://www.w3.org/2001/XMLSchema#integer">938</Aux:annotation_start>
				<Aux:annotation_end rdf:datatype="http://www.w3.org/2001/XMLSchema#integer">953</Aux:annotation_end>
				<Aux:instance rdf:nodeID="bnode38278070-3826-47B4-AB1A-23B6F4BD0FF1"/>
				<Aux:property_name xml:lang="en-US">http://www.abbyy.com/ns/BasicEntity#ms_major_currency</Aux:property_name>
				<Aux:property_value xml:lang="en-US">Spanish pesetas</Aux:property_value>
			</Aux:PropertyAnnotation>
		</Aux:annotation>
		<Aux:annotation>
			<Aux:PropertyAnnotation rdf:nodeID="bnode45E25C50-FC51-452C-AEA6-49E473A3D584">
				<Aux:annotation_start rdf:datatype="http://www.w3.org/2001/XMLSchema#integer">1012</Aux:annotation_start>
				<Aux:annotation_end rdf:datatype="http://www.w3.org/2001/XMLSchema#integer">1015</Aux:annotation_end>
				<Aux:instance rdf:nodeID="bnodeC28C7172-4AE5-460C-A654-0E7902C23290"/>
				<Aux:property_name xml:lang="en-US">http://www.abbyy.com/ns/BasicEntity#ms_major_amount</Aux:property_name>
				<Aux:property_value xml:lang="en-US">500</Aux:property_value>
			</Aux:PropertyAnnotation>
		</Aux:annotation>
		<Aux:annotation>
			<Aux:InstanceAnnotation rdf:nodeID="bnodeF291596A-AF70-4413-88AF-9BF8DC4B57A7">
				<Aux:annotation_start rdf:datatype="http://www.w3.org/2001/XMLSchema#integer">1012</Aux:annotation_start>
				<Aux:annotation_end rdf:datatype="http://www.w3.org/2001/XMLSchema#integer">1023</Aux:annotation_end>
				<Aux:instance rdf:nodeID="bnodeC28C7172-4AE5-460C-A654-0E7902C23290"/>
			</Aux:InstanceAnnotation>
		</Aux:annotation>
		<Aux:annotation>
			<Aux:PropertyAnnotation rdf:nodeID="bnode8DBB0011-756E-4D4B-B68F-19B81EA1A080">
				<Aux:annotation_start rdf:datatype="http://www.w3.org/2001/XMLSchema#integer">1016</Aux:annotation_start>
				<Aux:annotation_end rdf:datatype="http://www.w3.org/2001/XMLSchema#integer">1023</Aux:annotation_end>
				<Aux:instance rdf:nodeID="bnodeC28C7172-4AE5-460C-A654-0E7902C23290"/>
				<Aux:property_name xml:lang="en-US">http://www.abbyy.com/ns/BasicEntity#ms_major_currency</Aux:property_name>
				<Aux:property_value xml:lang="en-US">pesetas</Aux:property_value>
			</Aux:PropertyAnnotation>
		</Aux:annotation>
	</Aux:TextAnnotations>
</rdf:RDF>