<?xml version="1.0" encoding="UTF-8" standalone="no"?>
<?OntoDPSData docID="3373605" markupID="2092790" OntoTechnologyVersion="3.59.92.0"?>
<rdf:RDF xmlns:rdf="http://www.w3.org/1999/02/22-rdf-syntax-ns#" xmlns:BasicEntity="http://www.abbyy.com/ns/BasicEntity#" xmlns:rdfs="http://www.w3.org/2000/01/rdf-schema#" xmlns:Aux="http://www.abbyy.com/ns/Aux#">
	<BasicEntity:MoneySimplified rdf:nodeID="bnodeA1C0CD67-6DDD-4D2C-89C6-E11BD6997D1B">
		<BasicEntity:ms_major_currency xml:lang="en-US">VND</BasicEntity:ms_major_currency>
		<BasicEntity:ms_major_amount xml:lang="en-US">5000</BasicEntity:ms_major_amount>
	</BasicEntity:MoneySimplified>
	<Aux:TextAnnotations rdf:nodeID="bnode4632D0E5-4F47-4AC2-96A5-F671FD91B589">
		<Aux:document_text xml:lang="en-US">Traditionally, tò he craftsmen had a compact set of tools so that in one day they could go to several common places such as markets, communal temple grounds and especially local festivals where children often gathered to play or accompany their parents. According to the old generation of tò he craftsmen, the origin of tò he making was dated to the 17th century. The two most important occasions each year for tò he craftsmen are Tết and Trung Thu because they are the favorite festivals for Vietnamnese children. Nowadays, tò he is made and sold not only during the Tết holiday and other festivals but also all year round in public place like parks, gardens. The price for a figurine sold in Hanoi varies from 3,000 to 5,000 VND. There is a village in the countryside of Hanoi where many people earn their living by making and selling tò he, it is Xuân La village which has about 200 tò he craftsmen and almost all villagers from children to adults can make tò he figurine in a very brief period. Facing the threat from modern toys and other forms of entertainment, tò he craftsmen have to be more and more creative so that their figurines can appear more lively and closer to the children, for that reason tò he figurines today can be also modeled after characters from international films and cartoons such as Doraemon, Pikachu and even Sailor Moon with her very own blond hair.</Aux:document_text>
		<Aux:annotation>
			<Aux:InstanceAnnotation rdf:nodeID="bnodeA7B48CDE-3847-4F87-A47F-174E047DE93A">
				<Aux:annotation_start rdf:datatype="http://www.w3.org/2001/XMLSchema#integer">721</Aux:annotation_start>
				<Aux:annotation_end rdf:datatype="http://www.w3.org/2001/XMLSchema#integer">730</Aux:annotation_end>
				<Aux:instance rdf:nodeID="bnodeA1C0CD67-6DDD-4D2C-89C6-E11BD6997D1B"/>
			</Aux:InstanceAnnotation>
		</Aux:annotation>
		<Aux:annotation>
			<Aux:PropertyAnnotation rdf:nodeID="bnode48554754-97B7-4413-9B9B-6317B8B1E2A2">
				<Aux:annotation_start rdf:datatype="http://www.w3.org/2001/XMLSchema#integer">721</Aux:annotation_start>
				<Aux:annotation_end rdf:datatype="http://www.w3.org/2001/XMLSchema#integer">726</Aux:annotation_end>
				<Aux:instance rdf:nodeID="bnodeA1C0CD67-6DDD-4D2C-89C6-E11BD6997D1B"/>
				<Aux:property_name xml:lang="en-US">http://www.abbyy.com/ns/BasicEntity#ms_major_amount</Aux:property_name>
				<Aux:property_value xml:lang="en-US">5000</Aux:property_value>
			</Aux:PropertyAnnotation>
		</Aux:annotation>
		<Aux:annotation>
			<Aux:PropertyAnnotation rdf:nodeID="bnode082156A1-AEA5-4F16-AC05-8ACB29A49A04">
				<Aux:annotation_start rdf:datatype="http://www.w3.org/2001/XMLSchema#integer">727</Aux:annotation_start>
				<Aux:annotation_end rdf:datatype="http://www.w3.org/2001/XMLSchema#integer">730</Aux:annotation_end>
				<Aux:instance rdf:nodeID="bnodeA1C0CD67-6DDD-4D2C-89C6-E11BD6997D1B"/>
				<Aux:property_name xml:lang="en-US">http://www.abbyy.com/ns/BasicEntity#ms_major_currency</Aux:property_name>
				<Aux:property_value xml:lang="en-US">VND</Aux:property_value>
			</Aux:PropertyAnnotation>
		</Aux:annotation>
	</Aux:TextAnnotations>
</rdf:RDF>