<?xml version="1.0" encoding="UTF-8" standalone="no"?>
<?OntoDPSData docID="3375641" markupID="2092790" OntoTechnologyVersion="3.59.92.0"?>
<rdf:RDF xmlns:rdf="http://www.w3.org/1999/02/22-rdf-syntax-ns#" xmlns:BasicEntity="http://www.abbyy.com/ns/BasicEntity#" xmlns:rdfs="http://www.w3.org/2000/01/rdf-schema#" xmlns:Aux="http://www.abbyy.com/ns/Aux#">
	<BasicEntity:MoneySimplified rdf:nodeID="bnode28E87D8A-37D8-4455-BC33-62FF846E9EFD">
		<BasicEntity:ms_major_currency xml:lang="en-US">PHP</BasicEntity:ms_major_currency>
		<BasicEntity:ms_major_amount xml:lang="en-US">10523000</BasicEntity:ms_major_amount>
	</BasicEntity:MoneySimplified>
	<BasicEntity:MoneySimplified rdf:nodeID="bnodeF07DD290-F441-4F79-8C6E-FC36AE88E71B">
		<BasicEntity:ms_major_currency xml:lang="en-US">TWD</BasicEntity:ms_major_currency>
		<BasicEntity:ms_major_amount xml:lang="en-US">13800000</BasicEntity:ms_major_amount>
	</BasicEntity:MoneySimplified>
	<BasicEntity:MoneySimplified rdf:nodeID="bnode4A5D7AA7-1BD8-494B-BEE3-B17F1CA42A6C">
		<BasicEntity:ms_major_currency xml:lang="en-US">USD</BasicEntity:ms_major_currency>
		<BasicEntity:ms_major_amount xml:lang="en-US">200000</BasicEntity:ms_major_amount>
	</BasicEntity:MoneySimplified>
	<BasicEntity:MoneySimplified rdf:nodeID="bnode1A32791D-DD17-4915-BBCB-7EA5EEB49AB5">
		<BasicEntity:ms_major_currency xml:lang="en-US">JPY</BasicEntity:ms_major_currency>
		<BasicEntity:ms_major_amount xml:lang="en-US">90000000</BasicEntity:ms_major_amount>
	</BasicEntity:MoneySimplified>
	<BasicEntity:MoneySimplified rdf:nodeID="bnode6754A043-F517-4BDB-9BEA-CA016D755A5D">
		<BasicEntity:ms_major_currency xml:lang="en-US">KRW</BasicEntity:ms_major_currency>
		<BasicEntity:ms_major_amount xml:lang="en-US">370000000</BasicEntity:ms_major_amount>
	</BasicEntity:MoneySimplified>
	<Aux:TextAnnotations rdf:nodeID="bnodeF24BD707-2533-4F91-9F11-C7D3BA4CCE29">
		<Aux:document_text xml:lang="en-US"> JPY 90,000 thousand 100.0% Manufacturing, sales and maintenance of precision equipment in which semiconductors and/or other electronic components are applied Shinkawa Korea Co., Ltd. KRW 370,000 thousand 100.0% Sales promotion and maintenance services for semiconductor manufacturing equipment Shinkawa Taiwan Co., Ltd. TWD 13,800 thousand 100.0% Sales promotion and maintenance services for semiconductor manufacturing equipment Shinkawa (Shanghai) Co., Ltd. USD 200 thousand 100.0% Sales promotion and maintenance services for semiconductor manufacturing equipment Shinkawa Philippines, Inc. PHP 10,523 thousand 100.0% Maintenance services for semiconductor manufacturing equipment</Aux:document_text>
		<Aux:annotation>
			<Aux:InstanceAnnotation rdf:nodeID="bnodeAB3EE917-363B-4E4D-A330-5C26D141CAD4">
				<Aux:annotation_start rdf:datatype="http://www.w3.org/2001/XMLSchema#integer">1</Aux:annotation_start>
				<Aux:annotation_end rdf:datatype="http://www.w3.org/2001/XMLSchema#integer">20</Aux:annotation_end>
				<Aux:instance rdf:nodeID="bnode1A32791D-DD17-4915-BBCB-7EA5EEB49AB5"/>
			</Aux:InstanceAnnotation>
		</Aux:annotation>
		<Aux:annotation>
			<Aux:PropertyAnnotation rdf:nodeID="bnodeBD1E56B0-1D97-4599-8B35-CB6A3C600E26">
				<Aux:annotation_start rdf:datatype="http://www.w3.org/2001/XMLSchema#integer">1</Aux:annotation_start>
				<Aux:annotation_end rdf:datatype="http://www.w3.org/2001/XMLSchema#integer">4</Aux:annotation_end>
				<Aux:instance rdf:nodeID="bnode1A32791D-DD17-4915-BBCB-7EA5EEB49AB5"/>
				<Aux:property_name xml:lang="en-US">http://www.abbyy.com/ns/BasicEntity#ms_major_currency</Aux:property_name>
				<Aux:property_value xml:lang="en-US">JPY</Aux:property_value>
			</Aux:PropertyAnnotation>
		</Aux:annotation>
		<Aux:annotation>
			<Aux:PropertyAnnotation rdf:nodeID="bnodeB2CEF82C-812B-452D-924C-9E3D6EC91100">
				<Aux:annotation_start rdf:datatype="http://www.w3.org/2001/XMLSchema#integer">5</Aux:annotation_start>
				<Aux:annotation_end rdf:datatype="http://www.w3.org/2001/XMLSchema#integer">20</Aux:annotation_end>
				<Aux:instance rdf:nodeID="bnode1A32791D-DD17-4915-BBCB-7EA5EEB49AB5"/>
				<Aux:property_name xml:lang="en-US">http://www.abbyy.com/ns/BasicEntity#ms_major_amount</Aux:property_name>
				<Aux:property_value xml:lang="en-US">90000000</Aux:property_value>
			</Aux:PropertyAnnotation>
		</Aux:annotation>
		<Aux:annotation>
			<Aux:InstanceAnnotation rdf:nodeID="bnode5352CF70-5132-444B-9759-B2C522087B47">
				<Aux:annotation_start rdf:datatype="http://www.w3.org/2001/XMLSchema#integer">184</Aux:annotation_start>
				<Aux:annotation_end rdf:datatype="http://www.w3.org/2001/XMLSchema#integer">204</Aux:annotation_end>
				<Aux:instance rdf:nodeID="bnode6754A043-F517-4BDB-9BEA-CA016D755A5D"/>
			</Aux:InstanceAnnotation>
		</Aux:annotation>
		<Aux:annotation>
			<Aux:PropertyAnnotation rdf:nodeID="bnode7E8B1C91-6401-40E4-B8DE-D418EE215EBD">
				<Aux:annotation_start rdf:datatype="http://www.w3.org/2001/XMLSchema#integer">184</Aux:annotation_start>
				<Aux:annotation_end rdf:datatype="http://www.w3.org/2001/XMLSchema#integer">187</Aux:annotation_end>
				<Aux:instance rdf:nodeID="bnode6754A043-F517-4BDB-9BEA-CA016D755A5D"/>
				<Aux:property_name xml:lang="en-US">http://www.abbyy.com/ns/BasicEntity#ms_major_currency</Aux:property_name>
				<Aux:property_value xml:lang="en-US">KRW</Aux:property_value>
			</Aux:PropertyAnnotation>
		</Aux:annotation>
		<Aux:annotation>
			<Aux:PropertyAnnotation rdf:nodeID="bnode8616F196-E286-43F0-ABDF-CEF53D829FA2">
				<Aux:annotation_start rdf:datatype="http://www.w3.org/2001/XMLSchema#integer">188</Aux:annotation_start>
				<Aux:annotation_end rdf:datatype="http://www.w3.org/2001/XMLSchema#integer">204</Aux:annotation_end>
				<Aux:instance rdf:nodeID="bnode6754A043-F517-4BDB-9BEA-CA016D755A5D"/>
				<Aux:property_name xml:lang="en-US">http://www.abbyy.com/ns/BasicEntity#ms_major_amount</Aux:property_name>
				<Aux:property_value xml:lang="en-US">370000000</Aux:property_value>
			</Aux:PropertyAnnotation>
		</Aux:annotation>
		<Aux:annotation>
			<Aux:PropertyAnnotation rdf:nodeID="bnode413DAD50-59A0-458D-9E44-E9AFB77F8D77">
				<Aux:annotation_start rdf:datatype="http://www.w3.org/2001/XMLSchema#integer">321</Aux:annotation_start>
				<Aux:annotation_end rdf:datatype="http://www.w3.org/2001/XMLSchema#integer">324</Aux:annotation_end>
				<Aux:instance rdf:nodeID="bnodeF07DD290-F441-4F79-8C6E-FC36AE88E71B"/>
				<Aux:property_name xml:lang="en-US">http://www.abbyy.com/ns/BasicEntity#ms_major_currency</Aux:property_name>
				<Aux:property_value xml:lang="en-US">TWD</Aux:property_value>
			</Aux:PropertyAnnotation>
		</Aux:annotation>
		<Aux:annotation>
			<Aux:InstanceAnnotation rdf:nodeID="bnode0C91FDCF-0416-41B0-884E-752C03232301">
				<Aux:annotation_start rdf:datatype="http://www.w3.org/2001/XMLSchema#integer">321</Aux:annotation_start>
				<Aux:annotation_end rdf:datatype="http://www.w3.org/2001/XMLSchema#integer">340</Aux:annotation_end>
				<Aux:instance rdf:nodeID="bnodeF07DD290-F441-4F79-8C6E-FC36AE88E71B"/>
			</Aux:InstanceAnnotation>
		</Aux:annotation>
		<Aux:annotation>
			<Aux:PropertyAnnotation rdf:nodeID="bnode129AB64C-5BDE-4AE8-9C67-3898C6361286">
				<Aux:annotation_start rdf:datatype="http://www.w3.org/2001/XMLSchema#integer">325</Aux:annotation_start>
				<Aux:annotation_end rdf:datatype="http://www.w3.org/2001/XMLSchema#integer">340</Aux:annotation_end>
				<Aux:instance rdf:nodeID="bnodeF07DD290-F441-4F79-8C6E-FC36AE88E71B"/>
				<Aux:property_name xml:lang="en-US">http://www.abbyy.com/ns/BasicEntity#ms_major_amount</Aux:property_name>
				<Aux:property_value xml:lang="en-US">13800000</Aux:property_value>
			</Aux:PropertyAnnotation>
		</Aux:annotation>
		<Aux:annotation>
			<Aux:PropertyAnnotation rdf:nodeID="bnodeBB049E5C-4487-46C1-A553-1D0B2A457612">
				<Aux:annotation_start rdf:datatype="http://www.w3.org/2001/XMLSchema#integer">461</Aux:annotation_start>
				<Aux:annotation_end rdf:datatype="http://www.w3.org/2001/XMLSchema#integer">464</Aux:annotation_end>
				<Aux:instance rdf:nodeID="bnode4A5D7AA7-1BD8-494B-BEE3-B17F1CA42A6C"/>
				<Aux:property_name xml:lang="en-US">http://www.abbyy.com/ns/BasicEntity#ms_major_currency</Aux:property_name>
				<Aux:property_value xml:lang="en-US">USD</Aux:property_value>
			</Aux:PropertyAnnotation>
		</Aux:annotation>
		<Aux:annotation>
			<Aux:InstanceAnnotation rdf:nodeID="bnode0CB8CDCD-4ABC-42BE-B5E9-4AE3873C644C">
				<Aux:annotation_start rdf:datatype="http://www.w3.org/2001/XMLSchema#integer">461</Aux:annotation_start>
				<Aux:annotation_end rdf:datatype="http://www.w3.org/2001/XMLSchema#integer">477</Aux:annotation_end>
				<Aux:instance rdf:nodeID="bnode4A5D7AA7-1BD8-494B-BEE3-B17F1CA42A6C"/>
			</Aux:InstanceAnnotation>
		</Aux:annotation>
		<Aux:annotation>
			<Aux:PropertyAnnotation rdf:nodeID="bnode15E7222B-3724-40D7-85B0-D7DA957E1A44">
				<Aux:annotation_start rdf:datatype="http://www.w3.org/2001/XMLSchema#integer">465</Aux:annotation_start>
				<Aux:annotation_end rdf:datatype="http://www.w3.org/2001/XMLSchema#integer">477</Aux:annotation_end>
				<Aux:instance rdf:nodeID="bnode4A5D7AA7-1BD8-494B-BEE3-B17F1CA42A6C"/>
				<Aux:property_name xml:lang="en-US">http://www.abbyy.com/ns/BasicEntity#ms_major_amount</Aux:property_name>
				<Aux:property_value xml:lang="en-US">200000</Aux:property_value>
			</Aux:PropertyAnnotation>
		</Aux:annotation>
		<Aux:annotation>
			<Aux:InstanceAnnotation rdf:nodeID="bnode3FE8FCAC-2A6C-42AB-B257-8852FA5FD856">
				<Aux:annotation_start rdf:datatype="http://www.w3.org/2001/XMLSchema#integer">595</Aux:annotation_start>
				<Aux:annotation_end rdf:datatype="http://www.w3.org/2001/XMLSchema#integer">614</Aux:annotation_end>
				<Aux:instance rdf:nodeID="bnode28E87D8A-37D8-4455-BC33-62FF846E9EFD"/>
			</Aux:InstanceAnnotation>
		</Aux:annotation>
		<Aux:annotation>
			<Aux:PropertyAnnotation rdf:nodeID="bnode494A65ED-A55F-4E86-BD89-CB028CB89551">
				<Aux:annotation_start rdf:datatype="http://www.w3.org/2001/XMLSchema#integer">595</Aux:annotation_start>
				<Aux:annotation_end rdf:datatype="http://www.w3.org/2001/XMLSchema#integer">598</Aux:annotation_end>
				<Aux:instance rdf:nodeID="bnode28E87D8A-37D8-4455-BC33-62FF846E9EFD"/>
				<Aux:property_name xml:lang="en-US">http://www.abbyy.com/ns/BasicEntity#ms_major_currency</Aux:property_name>
				<Aux:property_value xml:lang="en-US">PHP</Aux:property_value>
			</Aux:PropertyAnnotation>
		</Aux:annotation>
		<Aux:annotation>
			<Aux:PropertyAnnotation rdf:nodeID="bnode0268D9E2-9263-491A-98A6-140789671209">
				<Aux:annotation_start rdf:datatype="http://www.w3.org/2001/XMLSchema#integer">599</Aux:annotation_start>
				<Aux:annotation_end rdf:datatype="http://www.w3.org/2001/XMLSchema#integer">614</Aux:annotation_end>
				<Aux:instance rdf:nodeID="bnode28E87D8A-37D8-4455-BC33-62FF846E9EFD"/>
				<Aux:property_name xml:lang="en-US">http://www.abbyy.com/ns/BasicEntity#ms_major_amount</Aux:property_name>
				<Aux:property_value xml:lang="en-US">10523000</Aux:property_value>
			</Aux:PropertyAnnotation>
		</Aux:annotation>
	</Aux:TextAnnotations>
</rdf:RDF>