<?xml version="1.0" encoding="UTF-8" standalone="no"?>
<?OntoDPSData docID="3375745" markupID="2092790" OntoTechnologyVersion="3.59.92.0"?>
<rdf:RDF xmlns:rdf="http://www.w3.org/1999/02/22-rdf-syntax-ns#" xmlns:BasicEntity="http://www.abbyy.com/ns/BasicEntity#" xmlns:rdfs="http://www.w3.org/2000/01/rdf-schema#" xmlns:Aux="http://www.abbyy.com/ns/Aux#">
	<BasicEntity:MoneySimplified rdf:nodeID="bnodeA9E46005-06AE-4765-8C81-AB182586CFA0">
		<BasicEntity:ms_major_currency xml:lang="en-US">zł</BasicEntity:ms_major_currency>
		<BasicEntity:ms_major_amount xml:lang="en-US">7000</BasicEntity:ms_major_amount>
	</BasicEntity:MoneySimplified>
	<BasicEntity:MoneySimplified rdf:nodeID="bnodeE25CB564-D45E-40FE-B518-9D230CC4F52C">
		<BasicEntity:ms_major_currency xml:lang="en-US">£</BasicEntity:ms_major_currency>
		<BasicEntity:ms_major_amount xml:lang="en-US">8000</BasicEntity:ms_major_amount>
	</BasicEntity:MoneySimplified>
	<BasicEntity:MoneySimplified rdf:nodeID="bnodeB0D330E7-EF1C-49DE-9D9A-F809B44057A9">
		<BasicEntity:ms_major_currency xml:lang="en-US">£</BasicEntity:ms_major_currency>
		<BasicEntity:ms_major_amount xml:lang="en-US">5454</BasicEntity:ms_major_amount>
	</BasicEntity:MoneySimplified>
	<BasicEntity:MoneySimplified rdf:nodeID="bnodeB9D95BAA-CF29-4008-9EDA-A0B0D95399CC">
		<BasicEntity:ms_major_currency xml:lang="en-US">£</BasicEntity:ms_major_currency>
		<BasicEntity:ms_major_amount xml:lang="en-US">1400</BasicEntity:ms_major_amount>
	</BasicEntity:MoneySimplified>
	<Aux:TextAnnotations rdf:nodeID="bnode3191C99B-60C9-4660-BE9D-0169B9C10007">
		<Aux:document_text xml:lang="en-US">The 105 was the last Syrena design. It was produced from 1972 to 1983 by the FSM factory and was badged accordingly. Unlike its predecessors it had regular front doors instead of "suicide" ones. The "Lux" version, produced from 1974, had the gear lever and handbrake between the front seats. The 105 served as a basis for two other models – Syrena R-20, which was a pick-up and a van – Bosto. A 1983 FSM Syrena 105L finished in yellow was featured in series 10 episode 10 of the British television program Wheeler Dealers. Presenter Mike Brewer purchased the car in Poland for zł7,000 (the equivalent of £1,400) and drove it back to the show's UK-based workshop where it underwent repairs and upgrades by mechanic Edd China. The colour was changed to red and white in homage to the Polish flag. Other work included upgrades to the steering box, refurbishing the drum brakes, replacing the dynamo with an alternator and replacing the radio. The total cost of procuring and upgrading the car reached £5454. The completed car was driven to the Polish embassy where ambassador Witold Sobków took a ride with them. The car was later sold for £8,000 to the bubble car museum in Lincolnshire.</Aux:document_text>
		<Aux:annotation>
			<Aux:InstanceAnnotation rdf:nodeID="bnode9A098C0A-2F38-4E5A-9EEF-83116E793559">
				<Aux:annotation_start rdf:datatype="http://www.w3.org/2001/XMLSchema#integer">577</Aux:annotation_start>
				<Aux:annotation_end rdf:datatype="http://www.w3.org/2001/XMLSchema#integer">584</Aux:annotation_end>
				<Aux:instance rdf:nodeID="bnodeA9E46005-06AE-4765-8C81-AB182586CFA0"/>
			</Aux:InstanceAnnotation>
		</Aux:annotation>
		<Aux:annotation>
			<Aux:PropertyAnnotation rdf:nodeID="bnode39E44DC3-E953-4EBE-9BE0-C2CA51483DFB">
				<Aux:annotation_start rdf:datatype="http://www.w3.org/2001/XMLSchema#integer">577</Aux:annotation_start>
				<Aux:annotation_end rdf:datatype="http://www.w3.org/2001/XMLSchema#integer">579</Aux:annotation_end>
				<Aux:instance rdf:nodeID="bnodeA9E46005-06AE-4765-8C81-AB182586CFA0"/>
				<Aux:property_name xml:lang="en-US">http://www.abbyy.com/ns/BasicEntity#ms_major_currency</Aux:property_name>
				<Aux:property_value xml:lang="en-US">zł</Aux:property_value>
			</Aux:PropertyAnnotation>
		</Aux:annotation>
		<Aux:annotation>
			<Aux:PropertyAnnotation rdf:nodeID="bnodeD8D8BDC1-A687-4FD4-A389-E7252D2DB27F">
				<Aux:annotation_start rdf:datatype="http://www.w3.org/2001/XMLSchema#integer">579</Aux:annotation_start>
				<Aux:annotation_end rdf:datatype="http://www.w3.org/2001/XMLSchema#integer">584</Aux:annotation_end>
				<Aux:instance rdf:nodeID="bnodeA9E46005-06AE-4765-8C81-AB182586CFA0"/>
				<Aux:property_name xml:lang="en-US">http://www.abbyy.com/ns/BasicEntity#ms_major_amount</Aux:property_name>
				<Aux:property_value xml:lang="en-US">7000</Aux:property_value>
			</Aux:PropertyAnnotation>
		</Aux:annotation>
		<Aux:annotation>
			<Aux:InstanceAnnotation rdf:nodeID="bnode7F39F84E-3639-4478-8B8D-6D747E1E2523">
				<Aux:annotation_start rdf:datatype="http://www.w3.org/2001/XMLSchema#integer">604</Aux:annotation_start>
				<Aux:annotation_end rdf:datatype="http://www.w3.org/2001/XMLSchema#integer">610</Aux:annotation_end>
				<Aux:instance rdf:nodeID="bnodeB9D95BAA-CF29-4008-9EDA-A0B0D95399CC"/>
			</Aux:InstanceAnnotation>
		</Aux:annotation>
		<Aux:annotation>
			<Aux:PropertyAnnotation rdf:nodeID="bnode50BF50A5-AFBE-417B-95EE-81398C1F6570">
				<Aux:annotation_start rdf:datatype="http://www.w3.org/2001/XMLSchema#integer">604</Aux:annotation_start>
				<Aux:annotation_end rdf:datatype="http://www.w3.org/2001/XMLSchema#integer">605</Aux:annotation_end>
				<Aux:instance rdf:nodeID="bnodeB9D95BAA-CF29-4008-9EDA-A0B0D95399CC"/>
				<Aux:property_name xml:lang="en-US">http://www.abbyy.com/ns/BasicEntity#ms_major_currency</Aux:property_name>
				<Aux:property_value xml:lang="en-US">£</Aux:property_value>
			</Aux:PropertyAnnotation>
		</Aux:annotation>
		<Aux:annotation>
			<Aux:PropertyAnnotation rdf:nodeID="bnode6B85C580-26DF-4AF5-A093-729BFFC9F28F">
				<Aux:annotation_start rdf:datatype="http://www.w3.org/2001/XMLSchema#integer">605</Aux:annotation_start>
				<Aux:annotation_end rdf:datatype="http://www.w3.org/2001/XMLSchema#integer">610</Aux:annotation_end>
				<Aux:instance rdf:nodeID="bnodeB9D95BAA-CF29-4008-9EDA-A0B0D95399CC"/>
				<Aux:property_name xml:lang="en-US">http://www.abbyy.com/ns/BasicEntity#ms_major_amount</Aux:property_name>
				<Aux:property_value xml:lang="en-US">1400</Aux:property_value>
			</Aux:PropertyAnnotation>
		</Aux:annotation>
		<Aux:annotation>
			<Aux:PropertyAnnotation rdf:nodeID="bnode3A8FEDF5-EB58-4E05-9CDA-7C00E3D71095">
				<Aux:annotation_start rdf:datatype="http://www.w3.org/2001/XMLSchema#integer">998</Aux:annotation_start>
				<Aux:annotation_end rdf:datatype="http://www.w3.org/2001/XMLSchema#integer">999</Aux:annotation_end>
				<Aux:instance rdf:nodeID="bnodeB0D330E7-EF1C-49DE-9D9A-F809B44057A9"/>
				<Aux:property_name xml:lang="en-US">http://www.abbyy.com/ns/BasicEntity#ms_major_currency</Aux:property_name>
				<Aux:property_value xml:lang="en-US">£</Aux:property_value>
			</Aux:PropertyAnnotation>
		</Aux:annotation>
		<Aux:annotation>
			<Aux:InstanceAnnotation rdf:nodeID="bnode0D476588-5AFB-4A3D-A206-91F076092F6F">
				<Aux:annotation_start rdf:datatype="http://www.w3.org/2001/XMLSchema#integer">998</Aux:annotation_start>
				<Aux:annotation_end rdf:datatype="http://www.w3.org/2001/XMLSchema#integer">1003</Aux:annotation_end>
				<Aux:instance rdf:nodeID="bnodeB0D330E7-EF1C-49DE-9D9A-F809B44057A9"/>
			</Aux:InstanceAnnotation>
		</Aux:annotation>
		<Aux:annotation>
			<Aux:PropertyAnnotation rdf:nodeID="bnodeD69C2656-D803-414E-B6B9-A5CA39343938">
				<Aux:annotation_start rdf:datatype="http://www.w3.org/2001/XMLSchema#integer">999</Aux:annotation_start>
				<Aux:annotation_end rdf:datatype="http://www.w3.org/2001/XMLSchema#integer">1003</Aux:annotation_end>
				<Aux:instance rdf:nodeID="bnodeB0D330E7-EF1C-49DE-9D9A-F809B44057A9"/>
				<Aux:property_name xml:lang="en-US">http://www.abbyy.com/ns/BasicEntity#ms_major_amount</Aux:property_name>
				<Aux:property_value xml:lang="en-US">5454</Aux:property_value>
			</Aux:PropertyAnnotation>
		</Aux:annotation>
		<Aux:annotation>
			<Aux:PropertyAnnotation rdf:nodeID="bnodeA04CAD7C-A45C-4702-97D0-BDEB1A4A402A">
				<Aux:annotation_start rdf:datatype="http://www.w3.org/2001/XMLSchema#integer">1137</Aux:annotation_start>
				<Aux:annotation_end rdf:datatype="http://www.w3.org/2001/XMLSchema#integer">1138</Aux:annotation_end>
				<Aux:instance rdf:nodeID="bnodeE25CB564-D45E-40FE-B518-9D230CC4F52C"/>
				<Aux:property_name xml:lang="en-US">http://www.abbyy.com/ns/BasicEntity#ms_major_currency</Aux:property_name>
				<Aux:property_value xml:lang="en-US">£</Aux:property_value>
			</Aux:PropertyAnnotation>
		</Aux:annotation>
		<Aux:annotation>
			<Aux:InstanceAnnotation rdf:nodeID="bnode625684A9-8B1B-443C-B73B-892787CCBF22">
				<Aux:annotation_start rdf:datatype="http://www.w3.org/2001/XMLSchema#integer">1137</Aux:annotation_start>
				<Aux:annotation_end rdf:datatype="http://www.w3.org/2001/XMLSchema#integer">1143</Aux:annotation_end>
				<Aux:instance rdf:nodeID="bnodeE25CB564-D45E-40FE-B518-9D230CC4F52C"/>
			</Aux:InstanceAnnotation>
		</Aux:annotation>
		<Aux:annotation>
			<Aux:PropertyAnnotation rdf:nodeID="bnode64B967AD-C6B4-4FA3-89D9-35A14F92D214">
				<Aux:annotation_start rdf:datatype="http://www.w3.org/2001/XMLSchema#integer">1138</Aux:annotation_start>
				<Aux:annotation_end rdf:datatype="http://www.w3.org/2001/XMLSchema#integer">1143</Aux:annotation_end>
				<Aux:instance rdf:nodeID="bnodeE25CB564-D45E-40FE-B518-9D230CC4F52C"/>
				<Aux:property_name xml:lang="en-US">http://www.abbyy.com/ns/BasicEntity#ms_major_amount</Aux:property_name>
				<Aux:property_value xml:lang="en-US">8000</Aux:property_value>
			</Aux:PropertyAnnotation>
		</Aux:annotation>
	</Aux:TextAnnotations>
</rdf:RDF>